{
    "config": {
        "model": "integrator",
        "sigma": 5.0,
        "degree": 2,
        "lr": 0.001,
        "epochs": 1000
    },
    "timestamp": "20260118_012324",
    "final_loss": 526.1062622070312,
    "equations": [
        "1.00000omega",
        "0.000541 + -0.04732theta + -0.00367omega + -0.01543theta^2 + 0.01739theta omega + -0.00484omega^2"
    ],
    "loss_history": {
        "0": 36557.9609375,
        "100": 18614.75,
        "200": 7916.732421875,
        "300": 3230.966796875,
        "400": 2196.548828125,
        "500": 1731.803955078125,
        "600": 1371.085693359375,
        "700": 1061.6077880859375,
        "800": 797.5048828125,
        "900": 632.42041015625
    },
    "scaling_params": {
        "mean_x": [
            -1.1126707792282104,
            0.0016096459003165364
        ],
        "std_x": [
            1.0855050086975098,
            0.012150955386459827
        ],
        "t_scale": 90.0
    }
}